odoo/addons/ssi_general_audit_worksheet_planning_memorandum/README.rst
odoo/addons/ssi_general_audit_worksheet_planning_memorandum/__init__.py
odoo/addons/ssi_general_audit_worksheet_planning_memorandum/__manifest__.py
odoo/addons/ssi_general_audit_worksheet_planning_memorandum/data/general_audit_worksheet_type_data.xml
odoo/addons/ssi_general_audit_worksheet_planning_memorandum/data/approval_template/general_audit_ws_fbbe0f8.xml
odoo/addons/ssi_general_audit_worksheet_planning_memorandum/data/ir_sequence/general_audit_ws_fbbe0f8.xml
odoo/addons/ssi_general_audit_worksheet_planning_memorandum/data/policy_template/general_audit_ws_fbbe0f8.xml
odoo/addons/ssi_general_audit_worksheet_planning_memorandum/data/sequence_template/general_audit_ws_fbbe0f8.xml
odoo/addons/ssi_general_audit_worksheet_planning_memorandum/models/__init__.py
odoo/addons/ssi_general_audit_worksheet_planning_memorandum/models/general_audit_ws_fbbe0f8.py
odoo/addons/ssi_general_audit_worksheet_planning_memorandum/security/ir_module_category_data.xml
odoo/addons/ssi_general_audit_worksheet_planning_memorandum/security/ir_model_access/general_audit_ws_fbbe0f8.xml
odoo/addons/ssi_general_audit_worksheet_planning_memorandum/security/ir_rule/general_audit_ws_fbbe0f8.xml
odoo/addons/ssi_general_audit_worksheet_planning_memorandum/security/res_group/general_audit_ws_fbbe0f8.xml
odoo/addons/ssi_general_audit_worksheet_planning_memorandum/static/description/icon.png
odoo/addons/ssi_general_audit_worksheet_planning_memorandum/views/general_audit_ws_fbbe0f8_views.xml
odoo14_addon_ssi_general_audit_worksheet_planning_memorandum-14.0.1.2.0.dist-info/METADATA
odoo14_addon_ssi_general_audit_worksheet_planning_memorandum-14.0.1.2.0.dist-info/WHEEL
odoo14_addon_ssi_general_audit_worksheet_planning_memorandum-14.0.1.2.0.dist-info/top_level.txt
odoo14_addon_ssi_general_audit_worksheet_planning_memorandum-14.0.1.2.0.dist-info/RECORD
